TumorDecon/DeconRNASeq.py
TumorDecon/SingScore.py
TumorDecon/__init__.py
TumorDecon/batch_correction.py
TumorDecon/cibersort.py
TumorDecon/data_utils.py
TumorDecon/hugoify.py
TumorDecon/signature_matrix.py
TumorDecon/ssGSEA.py
TumorDecon/tumor_deconvolve.py
TumorDecon/visualization.py
TumorDecon/data/Gene_sets.csv
TumorDecon/data/LM22.txt
TumorDecon/data/LM22_up_genes.csv
TumorDecon/data/LM6.txt
TumorDecon/data/LM6_up_genes.csv
TumorDecon/data/__init__.py
TumorDecon/data/coadred_data_RNA_Seq_v2_expression_median.txt
TumorDecon/data/kmeans_signature_matrix_qval.txt
TumorDecon/data/Simulation_data/__init__.py
TumorDecon/data/downloaded/__init__.py
TumorDecon/data/downloaded/readme.txt
TumorDecon/data/gene_ID_conversion/GSE87692_Primary_HsESF_TPMs_073015.txt
TumorDecon/data/gene_ID_conversion/hugo_enseml_synonym.txt
TumorDecon-1.1.1.dist-info/METADATA
TumorDecon-1.1.1.dist-info/RECORD
TumorDecon-1.1.1.dist-info/WHEEL
TumorDecon-1.1.1.dist-info/dependency_links.txt
TumorDecon-1.1.1.dist-info/top_level.txt
