Metadata-Version: 2.1
Name: TumorDecon
Version: 1.1.1
Summary: Deconvolution Methods for Digital Cytometry
Home-page: https://github.com/ShahriyariLab/TumorDecon
Author: ShahriyariLab
Author-email: lshahriyari@umass.edu
License: MIT License
Platform: UNKNOWN
Classifier: Programming Language :: Python :: 3
Classifier: License :: OSI Approved :: MIT License
Classifier: Operating System :: OS Independent
Requires-Python: >=3.6
Requires-Dist: scikit-learn (>0.20.3)
Requires-Dist: numpy (>1.18.2)
Requires-Dist: pandas (>1.0.3)
Requires-Dist: matplotlib (>2.2.2)
Requires-Dist: scipy (>1.2.1)
Requires-Dist: requests (>=2.23.0)
Requires-Dist: beautifulsoup4 (>4.6.0)
Requires-Dist: multiprocess (>=0.70.9)
Requires-Dist: seaborn (>0.10.0)
Requires-Dist: wget (>=3.2)
Requires-Dist: combat (>=0.2.1)
Requires-Dist: mpmath (>=1.1.0)
Requires-Dist: patsy (>=0.5.1)
Requires-Dist: statsmodels (>=0.9.0)
